MANIFEST.in
README.md
setup.py
fastapi_assistant/__init__.py
fastapi_assistant/builder_api.py
fastapi_assistant/builder_db_engine.py
fastapi_assistant/log_settings.py
fastapi_assistant.egg-info/PKG-INFO
fastapi_assistant.egg-info/SOURCES.txt
fastapi_assistant.egg-info/dependency_links.txt
fastapi_assistant.egg-info/requires.txt
fastapi_assistant.egg-info/top_level.txt
fastapi_assistant/bases/__init__.py
fastapi_assistant/bases/dao.py
fastapi_assistant/bases/enums.py
fastapi_assistant/bases/filter.py
fastapi_assistant/bases/model.py
fastapi_assistant/bases/schema.py
fastapi_assistant/bases/service.py
fastapi_assistant/bases/asyncio/__init__.py
fastapi_assistant/bases/asyncio/dao.py
fastapi_assistant/bases/asyncio/service.py
fastapi_assistant/core/__init__.py
fastapi_assistant/core/exceptions.py
fastapi_assistant/core/scheduler.py
fastapi_assistant/core/sqlalchemy.py
fastapi_assistant/core/sqlalchemy_asyncio.py
fastapi_assistant/libs/__init__.py
fastapi_assistant/libs/date_time.py
fastapi_assistant/libs/excel_tool.py
fastapi_assistant/libs/pagination.py
fastapi_assistant/libs/template_import.py
fastapi_assistant/static/favicon.png
fastapi_assistant/static/redoc.standalone.js
fastapi_assistant/static/swagger-ui-bundle.js
fastapi_assistant/static/swagger-ui.css